tf2calc/__init__.py
tf2calc/tf2calc.py
tf2calc-1.0.0.dist-info/LICENSE
tf2calc-1.0.0.dist-info/METADATA
tf2calc-1.0.0.dist-info/WHEEL
tf2calc-1.0.0.dist-info/top_level.txt
tf2calc-1.0.0.dist-info/RECORD
